.gitignore
MANIFEST.in
README.rst
bootstrap.py
buildout.cfg
setup.py
collective/__init__.py
collective.portlet.categories.egg-info/PKG-INFO
collective.portlet.categories.egg-info/SOURCES.txt
collective.portlet.categories.egg-info/dependency_links.txt
collective.portlet.categories.egg-info/entry_points.txt
collective.portlet.categories.egg-info/namespace_packages.txt
collective.portlet.categories.egg-info/not-zip-safe
collective.portlet.categories.egg-info/requires.txt
collective.portlet.categories.egg-info/top_level.txt
collective/portlet/__init__.py
collective/portlet/categories/__init__.py
collective/portlet/categories/categoriesportlet.pt
collective/portlet/categories/categoriesportlet.py
collective/portlet/categories/configure.zcml
collective/portlet/categories/interfaces.py
collective/portlet/categories/upgrades.py
collective/portlet/categories/upgrades.zcml
collective/portlet/categories/profiles/default/browserlayer.xml
collective/portlet/categories/profiles/default/cssregistry.xml
collective/portlet/categories/profiles/default/jsregistry.xml
collective/portlet/categories/profiles/default/metadata.xml
collective/portlet/categories/profiles/default/portlets.xml
collective/portlet/categories/tests/__init__.py
collective/portlet/categories/tests/base.py
collective/portlet/categories/tests/test_portlet.py
docs/HISTORY.txt